README.md
setup.cfg
setup.py
WebhookSite/WebhookSite.py
WebhookSite/__init__.py
WebhookSite.egg-info/PKG-INFO
WebhookSite.egg-info/SOURCES.txt
WebhookSite.egg-info/dependency_links.txt
WebhookSite.egg-info/not-zip-safe
WebhookSite.egg-info/top_level.txt