Metadata-Version: 2.1
Name: WebhookSite
Version: 0.1
Summary: Keywords to Interact with webhook.site
Author: Yamini Ambati
